<configs>
<append xpath="/blockplaceholders">	

	<placeholder name="guppycarsRandomHelper">
		<block name="guppyVehicleBlockSedan1" prob="0.05"/>
		<block name="guppyVehicleBlockSedan2" prob="0.05"/>
		<block name="guppyVehicleBlockPoliceCar" prob="0.05"/>
		<block name="guppyVehicleBlockAmbulance" prob="0.05"/>
		<block name="guppyVehicleBlockAmbulanceDamaged" prob="0.05"/>
		<block name="guppyVehicleBlockFiretruck" prob="0.05"/>
    <!--
		<block name="spawnvehicleGuppyAmbulance" prob="0.05"/>
		<block name="cntCar03SedanDamage0v04" prob="0.05"/>
		<block name="spawnvehicleGuppyAmbulanceDamaged" prob="0.05"/>
		<block name="spawnvehicleGuppyPoliceCar" prob="0.05"/>
		<block name="spawnvehicleGuppyMilitaryTruck" prob="0.05"/>
		<block name="spawnvehicleGuppyMilitaryCar" prob="0.05"/>    
    -->
	</placeholder>
  
</append>
</configs> 